[{"Estacion": "Terminal San Jer\u00f3nimo", "L\u00edneas": 1, "latitude": 21.149718, "longitude": -101.674926, "values": 25, "sens": 0.0, "ordre": 1.0, "next_sens": 0.0, "next_longitude": -101.680353, "next_latitude": 21.147535, "next_ordre": 2.0}, {"Estacion": "Los G\u00f3mez", "L\u00edneas": 1, "latitude": 21.147535, "longitude": -101.680353, "values": 33, "sens": 0.0, "ordre": 2.0, "next_sens": 0.0, "next_longitude": -101.684329, "next_latitude": 21.147219, "next_ordre": 3.0}, {"Estacion": "Pe\u00f1itas", "L\u00edneas": 1, "latitude": 21.147219, "longitude": -101.684329, "values": 48, "sens": 0.0, "ordre": 3.0, "next_sens": 0.0, "next_longitude": -101.685385, "next_latitude": 21.145872, "next_ordre": 4.0}, {"Estacion": "Lluvia", "L\u00edneas": 1, "latitude": 21.145872, "longitude": -101.685385, "values": 29, "sens": 0.0, "ordre": 4.0, "next_sens": 0.0, "next_longitude": -101.68571, "next_latitude": 21.144145, "next_ordre": 5.0}, {"Estacion": "Insurgentes", "L\u00edneas": 1, "latitude": 21.144145, "longitude": -101.68571, "values": 17, "sens": 0.0, "ordre": 5.0, "next_sens": 0.0, "next_longitude": -101.686494, "next_latitude": 21.139589, "next_ordre": 6.0}, {"Estacion": "IMSS T-1", "L\u00edneas": 1, "latitude": 21.139589, "longitude": -101.686494, "values": 38, "sens": 0.0, "ordre": 6.0, "next_sens": 0.0, "next_longitude": -101.687041, "next_latitude": 21.136693, "next_ordre": 7.0}, {"Estacion": "Calvario", "L\u00edneas": 1, "latitude": 21.136693, "longitude": -101.687041, "values": 50, "sens": 0.0, "ordre": 7.0, "next_sens": 0.0, "next_longitude": -101.687892, "next_latitude": 21.132199, "next_ordre": 8.0}, {"Estacion": "Parque Hidalgo", "L\u00edneas": 1, "latitude": 21.132199, "longitude": -101.687892, "values": 60, "sens": 0.0, "ordre": 8.0, "next_sens": 0.0, "next_longitude": -101.687626, "next_latitude": 21.12957, "next_ordre": 9.0}, {"Estacion": "Apolo", "L\u00edneas": 1, "latitude": 21.12957, "longitude": -101.687626, "values": 61, "sens": 0.0, "ordre": 9.0, "next_sens": 0.0, "next_longitude": -101.68327, "next_latitude": 21.125982, "next_ordre": 10.0}, {"Estacion": "Centro Hist\u00f3rico", "L\u00edneas": 1, "latitude": 21.125982, "longitude": -101.68327, "values": 26, "sens": 0.0, "ordre": 10.0, "next_sens": 0.0, "next_longitude": -101.679032, "next_latitude": 21.124357, "next_ordre": 11.0}, {"Estacion": "Hermanos Aldama", "L\u00edneas": 1, "latitude": 21.124357, "longitude": -101.679032, "values": 67, "sens": 0.0, "ordre": 11.0, "next_sens": 0.0, "next_longitude": -101.674561, "next_latitude": 21.122646, "next_ordre": 12.0}, {"Estacion": "Expiatorio", "L\u00edneas": 1, "latitude": 21.122646, "longitude": -101.674561, "values": 75, "sens": 0.0, "ordre": 12.0, "next_sens": 0.0, "next_longitude": -101.670333, "next_latitude": 21.121014, "next_ordre": 13.0}, {"Estacion": "Trigo", "L\u00edneas": 1, "latitude": 21.121014, "longitude": -101.670333, "values": 21, "sens": 0.0, "ordre": 13.0, "next_sens": 0.0, "next_longitude": -101.66561, "next_latitude": 21.119409, "next_ordre": 14.0}, {"Estacion": "Zona Piel", "L\u00edneas": 1, "latitude": 21.119409, "longitude": -101.66561, "values": 56, "sens": 0.0, "ordre": 14.0, "next_sens": 0.0, "next_longitude": -101.661094, "next_latitude": 21.118058, "next_ordre": 15.0}, {"Estacion": "Central Camionera", "L\u00edneas": 1, "latitude": 21.118058, "longitude": -101.661094, "values": 17, "sens": 0.0, "ordre": 15.0, "next_sens": 0.0, "next_longitude": -101.655556, "next_latitude": 21.115932, "next_ordre": 16.0}, {"Estacion": "Polif\u00f3rum", "L\u00edneas": 1, "latitude": 21.115932, "longitude": -101.655556, "values": 77, "sens": 0.0, "ordre": 16.0, "next_sens": 0.0, "next_longitude": -101.649421, "next_latitude": 21.112685, "next_ordre": 17.0}, {"Estacion": "Bugambilias", "L\u00edneas": 1, "latitude": 21.112685, "longitude": -101.649421, "values": 39, "sens": 0.0, "ordre": 17.0, "next_sens": 0.0, "next_longitude": -101.644879, "next_latitude": 21.109243, "next_ordre": 18.0}, {"Estacion": "Manzanares", "L\u00edneas": 1, "latitude": 21.109243, "longitude": -101.644879, "values": 25, "sens": 0.0, "ordre": 18.0, "next_sens": 0.0, "next_longitude": -101.641372, "next_latitude": 21.106546, "next_ordre": 19.0}, {"Estacion": "San Pedro", "L\u00edneas": 1, "latitude": 21.106546, "longitude": -101.641372, "values": 75, "sens": 0.0, "ordre": 19.0, "next_sens": 0.0, "next_longitude": -101.63785, "next_latitude": 21.103892, "next_ordre": 20.0}, {"Estacion": "Deportiva", "L\u00edneas": 1, "latitude": 21.103892, "longitude": -101.63785, "values": 27, "sens": 0.0, "ordre": 20.0, "next_sens": 0.0, "next_longitude": -101.634129, "next_latitude": 21.101056, "next_ordre": 21.0}, {"Estacion": "Juli\u00e1n de Obreg\u00f3n", "L\u00edneas": 1, "latitude": 21.101056, "longitude": -101.634129, "values": 49, "sens": 0.0, "ordre": 21.0, "next_sens": 0.0, "next_longitude": -101.630862, "next_latitude": 21.098497, "next_ordre": 22.0}, {"Estacion": "Cerrito de Jer\u00e9z", "L\u00edneas": 1, "latitude": 21.098497, "longitude": -101.630862, "values": 80, "sens": 0.0, "ordre": 22.0, "next_sens": 0.0, "next_longitude": -101.617803, "next_latitude": 21.094545, "next_ordre": 23.0}, {"Estacion": "Terminal Delta", "L\u00edneas": 1, "latitude": 21.094545, "longitude": -101.617803, "values": 70, "sens": 0.0, "ordre": 23.0, "next_sens": 1.0, "next_longitude": -101.630862, "next_latitude": 21.098497, "next_ordre": 24.0}, {"Estacion": "Cerrito de Jer\u00e9z", "L\u00edneas": 1, "latitude": 21.098497, "longitude": -101.630862, "values": 80, "sens": 1.0, "ordre": 24.0, "next_sens": 1.0, "next_longitude": -101.634129, "next_latitude": 21.101056, "next_ordre": 25.0}, {"Estacion": "Juli\u00e1n de Obreg\u00f3n", "L\u00edneas": 1, "latitude": 21.101056, "longitude": -101.634129, "values": 49, "sens": 1.0, "ordre": 25.0, "next_sens": 1.0, "next_longitude": -101.63785, "next_latitude": 21.103892, "next_ordre": 26.0}, {"Estacion": "Deportiva", "L\u00edneas": 1, "latitude": 21.103892, "longitude": -101.63785, "values": 27, "sens": 1.0, "ordre": 26.0, "next_sens": 1.0, "next_longitude": -101.641372, "next_latitude": 21.106546, "next_ordre": 27.0}, {"Estacion": "San Pedro", "L\u00edneas": 1, "latitude": 21.106546, "longitude": -101.641372, "values": 75, "sens": 1.0, "ordre": 27.0, "next_sens": 1.0, "next_longitude": -101.644879, "next_latitude": 21.109243, "next_ordre": 28.0}, {"Estacion": "Manzanares", "L\u00edneas": 1, "latitude": 21.109243, "longitude": -101.644879, "values": 25, "sens": 1.0, "ordre": 28.0, "next_sens": 1.0, "next_longitude": -101.649421, "next_latitude": 21.112685, "next_ordre": 29.0}, {"Estacion": "Bugambilias", "L\u00edneas": 1, "latitude": 21.112685, "longitude": -101.649421, "values": 39, "sens": 1.0, "ordre": 29.0, "next_sens": 1.0, "next_longitude": -101.655556, "next_latitude": 21.115932, "next_ordre": 30.0}, {"Estacion": "Polif\u00f3rum", "L\u00edneas": 1, "latitude": 21.115932, "longitude": -101.655556, "values": 77, "sens": 1.0, "ordre": 30.0, "next_sens": 1.0, "next_longitude": -101.661094, "next_latitude": 21.118058, "next_ordre": 31.0}, {"Estacion": "Central Camionera", "L\u00edneas": 1, "latitude": 21.118058, "longitude": -101.661094, "values": 17, "sens": 1.0, "ordre": 31.0, "next_sens": 1.0, "next_longitude": -101.66561, "next_latitude": 21.119409, "next_ordre": 32.0}, {"Estacion": "Zona Piel", "L\u00edneas": 1, "latitude": 21.119409, "longitude": -101.66561, "values": 56, "sens": 1.0, "ordre": 32.0, "next_sens": 1.0, "next_longitude": -101.670333, "next_latitude": 21.121014, "next_ordre": 33.0}, {"Estacion": "Trigo", "L\u00edneas": 1, "latitude": 21.121014, "longitude": -101.670333, "values": 21, "sens": 1.0, "ordre": 33.0, "next_sens": 1.0, "next_longitude": -101.674561, "next_latitude": 21.122646, "next_ordre": 34.0}, {"Estacion": "Expiatorio", "L\u00edneas": 1, "latitude": 21.122646, "longitude": -101.674561, "values": 75, "sens": 1.0, "ordre": 34.0, "next_sens": 1.0, "next_longitude": -101.679032, "next_latitude": 21.124357, "next_ordre": 35.0}, {"Estacion": "Hermanos Aldama", "L\u00edneas": 1, "latitude": 21.124357, "longitude": -101.679032, "values": 67, "sens": 1.0, "ordre": 35.0, "next_sens": 1.0, "next_longitude": -101.68327, "next_latitude": 21.125982, "next_ordre": 36.0}, {"Estacion": "Centro Hist\u00f3rico", "L\u00edneas": 1, "latitude": 21.125982, "longitude": -101.68327, "values": 26, "sens": 1.0, "ordre": 36.0, "next_sens": 1.0, "next_longitude": -101.687626, "next_latitude": 21.12957, "next_ordre": 37.0}, {"Estacion": "Apolo", "L\u00edneas": 1, "latitude": 21.12957, "longitude": -101.687626, "values": 61, "sens": 1.0, "ordre": 37.0, "next_sens": 1.0, "next_longitude": -101.687892, "next_latitude": 21.132199, "next_ordre": 38.0}, {"Estacion": "Parque Hidalgo", "L\u00edneas": 1, "latitude": 21.132199, "longitude": -101.687892, "values": 60, "sens": 1.0, "ordre": 38.0, "next_sens": 1.0, "next_longitude": -101.687041, "next_latitude": 21.136693, "next_ordre": 39.0}, {"Estacion": "Calvario", "L\u00edneas": 1, "latitude": 21.136693, "longitude": -101.687041, "values": 50, "sens": 1.0, "ordre": 39.0, "next_sens": 1.0, "next_longitude": -101.686494, "next_latitude": 21.139589, "next_ordre": 40.0}, {"Estacion": "IMSS T-1", "L\u00edneas": 1, "latitude": 21.139589, "longitude": -101.686494, "values": 38, "sens": 1.0, "ordre": 40.0, "next_sens": 1.0, "next_longitude": -101.68571, "next_latitude": 21.144145, "next_ordre": 41.0}, {"Estacion": "Insurgentes", "L\u00edneas": 1, "latitude": 21.144145, "longitude": -101.68571, "values": 17, "sens": 1.0, "ordre": 41.0, "next_sens": 1.0, "next_longitude": -101.685385, "next_latitude": 21.145872, "next_ordre": 42.0}, {"Estacion": "Lluvia", "L\u00edneas": 1, "latitude": 21.145872, "longitude": -101.685385, "values": 29, "sens": 1.0, "ordre": 42.0, "next_sens": 1.0, "next_longitude": -101.684329, "next_latitude": 21.147219, "next_ordre": 43.0}, {"Estacion": "Pe\u00f1itas", "L\u00edneas": 1, "latitude": 21.147219, "longitude": -101.684329, "values": 48, "sens": 1.0, "ordre": 43.0, "next_sens": 1.0, "next_longitude": -101.680353, "next_latitude": 21.147535, "next_ordre": 44.0}, {"Estacion": "Los G\u00f3mez", "L\u00edneas": 1, "latitude": 21.147535, "longitude": -101.680353, "values": 33, "sens": 1.0, "ordre": 44.0, "next_sens": 1.0, "next_longitude": -101.674926, "next_latitude": 21.149718, "next_ordre": 45.0}, {"Estacion": "Terminal San Jer\u00f3nimo", "L\u00edneas": 1, "latitude": 21.149718, "longitude": -101.674926, "values": 25, "sens": 1.0, "ordre": 45.0, "next_sens": 0.0, "next_longitude": 0.0, "next_latitude": 0.0, "next_ordre": 0.0}]